README.md
setup.py
lib/daze/__init__.py
lib/daze/daze.py
lib/daze/measures.py
lib/daze.egg-info/PKG-INFO
lib/daze.egg-info/SOURCES.txt
lib/daze.egg-info/dependency_links.txt
lib/daze.egg-info/requires.txt
lib/daze.egg-info/top_level.txt
lib/test/__init__.py
lib/test/lib/__init__.py
lib/test/lib/test_daze.py