Metadata-Version: 2.1
Name: daze
Version: 0.1.1
Summary: Better multi-class confusion matrix plots for Scikit-Learn, incorporating per-class and overall evaluation measures.
Home-page: https://github.com/eonu/daze
Author: Edwin Onuonga
Author-email: ed@eonu.net
License: MIT
Project-URL: Documentation, https://daze.readthedocs.io/en/latest
Project-URL: Bug Tracker, https://github.com/eonu/daze/issues
Project-URL: Source Code, https://github.com/eonu/daze
Platform: UNKNOWN
Classifier: Development Status :: 2 - Pre-Alpha
Classifier: Programming Language :: Python :: 3.5
Classifier: Programming Language :: Python :: 3.6
Classifier: Programming Language :: Python :: 3.7
Classifier: Programming Language :: Python :: 3.8
Classifier: Programming Language :: Python :: 3.9
Classifier: License :: OSI Approved :: MIT License
Classifier: Operating System :: Unix
Classifier: Operating System :: MacOS
Classifier: Intended Audience :: Science/Research
Classifier: Topic :: Software Development
Classifier: Topic :: Scientific/Engineering
Classifier: Natural Language :: English
Requires-Python: >=3.5,<3.10
